mksync/__init__.py
mksync/__main__.py
mksync/context.py
mksync/py.typed
mksync/readfile.py
mksync/targets.py
mksync/directives/__init__.py
mksync/directives/generic.py
mksync/directives/include.py
mksync/directives/parser.py
mksync/directives/runcmd.py
mksync/directives/toc.py
mksync-0.1.6.dist-info/METADATA
mksync-0.1.6.dist-info/WHEEL
mksync-0.1.6.dist-info/entry_points.txt
mksync-0.1.6.dist-info/licenses/LICENSE
mksync-0.1.6.dist-info/RECORD
