Metadata-Version: 2.4
Name: mksync
Version: 0.1.6
Project-URL: Bug Tracker, https://github.com/NiklasRosenstein/mksync/issues
Project-URL: Repository, https://github.com/NiklasRosenstein/mksync
Author-email: Niklas Rosenstein <rosensteinniklas@gmail.com>
License-Expression: MIT
License-File: LICENSE
Requires-Python: >=3.10
Requires-Dist: python-adjudicator<0.6,>=0.5.1
